arborq.py
arborq-0.9.2b3.dist-info/DESCRIPTION.rst
arborq-0.9.2b3.dist-info/METADATA
arborq-0.9.2b3.dist-info/metadata.json
arborq-0.9.2b3.dist-info/RECORD
arborq-0.9.2b3.dist-info/top_level.txt
arborq-0.9.2b3.dist-info/WHEEL
