Metadata-Version: 2.0
Name: arborq
Version: 0.9.2b3
Summary: A Python package to query Arbor PeakFlow SP devices.
Home-page: https://github.com/esnet/arborq
Author: Jon M. Dugan
Author-email: jdugan@es.net
License: BSD
Keywords: network measurement
Platform: UNKNOWN
Classifier: Development Status :: 5 - Production/Stable
Classifier: Intended Audience :: Developers
Classifier: Topic :: System :: Networking :: Monitoring
Classifier: Programming Language :: Python :: 2.7
Requires-Dist: requests
Requires-Dist: pytz
Requires-Dist: pypond
Provides-Extra: test
Requires-Dist: pytest; extra == 'test'
